[{"variant":"Or","fields":["Y",{"variant":"Add","fields":[{"variant":"Or","fields":[{"variant":"And","fields":[{"variant":"Or","fields":["T","T"]},"X"]},{"variant":"Add","fields":[{"variant":"Or","fields":["X","X"]},"X"]}]},{"variant":"And","fields":["Y","T"]}]}]},{"variant":"Xor","fields":[{"variant":"Xor","fields":[{"variant":"And","fields":[{"variant":"And","fields":["X",{"variant":"Xor","fields":["T","X"]}]},{"variant":"And","fields":[{"variant":"Or","fields":["Y","X"]},"Y"]}]},{"variant":"Sub","fields":[{"variant":"And","fields":["X",{"variant":"Or","fields":["Y","X"]}]},"X"]}]},{"variant":"Sub","fields":["Y","Y"]}]},{"variant":"Or","fields":["X",{"variant":"And","fields":[{"variant":"Mul","fields":[{"variant":"Or","fields":[{"variant":"Or","fields":["X","X"]},"T"]},{"variant":"Xor","fields":[{"variant":"Add","fields":["Y","X"]},"T"]}]},{"variant":"Or","fields":["X","X"]}]}]}]